{"status":"1","info":"OK","infocode":"10000","count":"46","suggestion":{"keywords":[],"cities":[]},"pois":[{"id":"B0JG3KTC4D","parent":[],"childtype":[],"name":"汽车充电站(铜陵精达综合智慧能源项目)","tag":[],"type":"汽车服务;充电站;充电站","typecode":"011100","biz_type":[],"address":"铜官山区虚镇五松社区五松卫生服务站五松花苑住宅小区","location":"117.800000,30.930000","tel":"13851871633","postcode":[],"website":[],"email":[],"pcode":"340000","pname":"安徽省","citycode":"0562","cityname":"铜陵市","adcode":"340705","adname":"铜官区","importance":[],"shopid":[],"shopinfo":"0","poiweight":[],"gridcode":"4617361410","distance":[],"navi_poiid":[],"entr_location":[],"business_area":[],"exit_location":[],"match":"0","recommend":"0","timestamp":"2023-04-20 07:46:25","alias":[],"indoor_map":"0","indoor_data":{"cpid":[],"floor":[],"truefloor":[],"cmsid":[]},"groupbuy_num":"0","discount_num":"0","biz_ext":{"rating":"2.7","cost":[]},"event":[],"children":[],"photos":[{"title":[],"url":"http://store.is.autonavi.com/showpic/5b3c256951374c48c9f54ca4a7834172"}]},{"id":"B0GDRMBUBH","parent":[],"childtype":[],"name":"义安大道充电站","tag":[],"type":"汽车服务;汽车服务相关;汽车服务相关","typecode":"010000","biz_type":[],"address":"义安大道北段疾控中心北侧路口进入","location":"117.816874,30.932951","tel":[],"postcode":[],"website":[],"email":[],"pcode":"340000","pname":"安徽省","citycode":"0562","cityname":"铜陵市","adcode":"340705","adname":"铜官区","importance":[],"shopid":[],"shopinfo":"0","poiweight":[],"gridcode":"4617361521","distance":[],"navi_poiid":[],"entr_location":"117.816999,30.932812","business_area":"义安路","exit_location":[],"match":"0","recommend":"0","timestamp":"2022-11-26 18:47:53","alias":[],"indoor_map":"0","indoor_data":{"cpid":[],"floor":[],"truefloor":[],"cmsid":[]},"groupbuy_num":"0","discount_num":"0","biz_ext":{"rating":[],"cost":[]},"event":[],"children":[],"photos":[]},{"id":"B0HKFO2T3M","parent":[],"childtype":[],"name":"杭州好充汽车充电站(铜陵市铜官区政府地上停车场)","tag":[],"type":"汽车服务;充电站;充电站","typecode":"011100","biz_type":[],"address":"九华山大道与铜井路交叉口北120米","location":"117.857158,30.935764","tel":[],"postcode":[],"website":[],"email":[],"pcode":"340000","pname":"安徽省","citycode":"0562","cityname":"铜陵市","adcode":"340705","adname":"铜官区","importance":[],"shopid":[],"shopinfo":"0","poiweight":[],"gridcode":"4617362801","distance":[],"navi_poiid":[],"entr_location":[],"business_area":[],"exit_location":[],"match":"0","recommend":"0","timestamp":"2023-03-14 14:38:14","alias":[],"indoor_map":"0","indoor_data":{"cpid":[],"floor":[],"truefloor":[],"cmsid":[]},"groupbuy_num":"0","discount_num":"0","biz_ext":{"rating":[],"cost":[]},"event":[],"children":[],"photos":[]},{"id":"B0HUH5L7D6","parent":[],"childtype":[],"name":"国家电网汽车充电站(铜陵市政务服务中心北停车场充电站)","tag":[],"type":"汽车服务;充电站;充电站","typecode":"011100","biz_type":[],"address":"湖东路与铜园南路交叉口西北280米","location":"117.811448,30.945393","tel":[],"postcode":[],"website":[],"email":[],"pcode":"340000","pname":"安徽省","citycode":"0562","cityname":"铜陵市","adcode":"340705","adname":"铜官区","importance":[],"shopid":[],"shopinfo":"0","poiweight":[],"gridcode":"4617363412","distance":[],"navi_poiid":[],"entr_location":[],"business_area":[],"exit_location":[],"match":"0","recommend":"0","timestamp":"2023-03-20 19:29:33","alias":[],"indoor_map":"0","indoor_data":{"cpid":[],"floor":[],"truefloor":[],"cmsid":[]},"groupbuy_num":"0","discount_num":"0","biz_ext":{"rating":[],"cost":[]},"event":[],"children":[],"photos":[]},{"id":"B0H2GUVKZ5","parent":[],"childtype":[],"name":"铜陵七星酒店管理有限公司汽车充电站","tag":[],"type":"汽车服务;充电站;充电站","typecode":"011100","biz_type":[],"address":"义安大道南段91号(距中央广场100米)海友酒店(铜陵步行街店)","location":"117.817085,30.925620","tel":"4000826699","postcode":[],"website":[],"email":[],"pcode":"340000","pname":"安徽省","citycode":"0562","cityname":"铜陵市","adcode":"340705","adname":"铜官区","importance":[],"shopid":[],"shopinfo":"0","poiweight":[],"gridcode":"4617361501","distance":[],"navi_poiid":[],"entr_location":"117.817261,30.925482","business_area":"义安路","exit_location":[],"match":"0","recommend":"0","timestamp":"2023-04-20 07:50:24","alias":[],"indoor_map":"0","indoor_data":{"cpid":[],"floor":[],"truefloor":[],"cmsid":[]},"groupbuy_num":"0","discount_num":"0","biz_ext":{"rating":"1.8","cost":[]},"event":[],"children":[],"photos":[{"title":[],"url":"http://store.is.autonavi.com/showpic/ee79d1c131c2c7940d89704ebf29ba62"}]},{"id":"B0I6V54XDA","parent":"B0IDCMOHZE","childtype":"313","name":"小鹏超级充电站","tag":[],"type":"汽车服务;汽车服务相关;汽车服务相关","typecode":"010000","biz_type":[],"address":"万达广场(铜陵店)地下停车场","location":"117.830989,30.944654","tel":[],"postcode":[],"website":[],"email":[],"pcode":"340000","pname":"安徽省","citycode":"0562","cityname":"铜陵市","adcode":"340705","adname":"铜官区","importance":[],"shopid":[],"shopinfo":"0","poiweight":[],"gridcode":"4617363611","distance":[],"navi_poiid":[],"entr_location":[],"business_area":"石城大道中段","exit_location":[],"match":"0","recommend":"0","timestamp":"2023-03-13 20:24:47","alias":[],"indoor_map":"0","indoor_data":{"cpid":[],"floor":[],"truefloor":[],"cmsid":[]},"groupbuy_num":"0","discount_num":"0","biz_ext":{"rating":[],"cost":[]},"event":[],"children":[],"photos":[{"title":[],"url":"http://store.is.autonavi.com/showpic/bef94af411d9048de271602d4561ba81"}]},{"id":"B0JA668VY8","parent":[],"childtype":[],"name":"特来电充电站(邻嘉城运朝山村)","tag":[],"type":"汽车服务;充电站;充电站","typecode":"011100","biz_type":[],"address":"朝山村","location":"117.902243,30.913782","tel":"4001300001","postcode":[],"website":[],"email":[],"pcode":"340000","pname":"安徽省","citycode":"0562","cityname":"铜陵市","adcode":"340705","adname":"铜官区","importance":[],"shopid":[],"shopinfo":"0","poiweight":[],"gridcode":"4617279210","distance":[],"navi_poiid":[],"entr_location":[],"business_area":[],"exit_location":[],"match":"0","recommend":"0","timestamp":"2023-04-16 06:55:17","alias":[],"indoor_map":"0","indoor_data":{"cpid":[],"floor":[],"truefloor":[],"cmsid":[]},"groupbuy_num":"0","discount_num":"0","biz_ext":{"rating":"2.7","cost":[]},"event":[],"children":[],"photos":[{"title":[],"url":"http://store.is.autonavi.com/showpic/6f0b289dbec7311c2e07352327d3db02"},{"title":[],"url":"http://store.is.autonavi.com/showpic/98d2f9443b0f1b958bd3d048f1cd6a1e"},{"title":[],"url":"http://store.is.autonavi.com/showpic/e456646d978ed6ea7f5bbc53f62e2ebb"}]},{"id":"B0I1NS5A56","parent":[],"childtype":[],"name":"特斯拉超级充电站(铜陵邻嘉城运西湖南邻里中心)","tag":[],"type":"汽车服务;充电站;充电站","typecode":"011100","biz_type":[],"address":"新庙王路与翠湖二路交叉口西北200米","location":"117.868911,30.954211","tel":"4009100707","postcode":[],"website":[],"email":[],"pcode":"340000","pname":"安徽省","citycode":"0562","cityname":"铜陵市","adcode":"340705","adname":"铜官区","importance":[],"shopid":[],"shopinfo":"0","poiweight":[],"gridcode":"4617364911","distance":[],"navi_poiid":[],"entr_location":"117.868911,30.954247","business_area":[],"exit_location":[],"match":"0","recommend":"0","timestamp":"2023-01-22 20:47:41","alias":[],"indoor_map":"0","indoor_data":{"cpid":[],"floor":[],"truefloor":[],"cmsid":[]},"groupbuy_num":"0","discount_num":"0","biz_ext":{"rating":"1.8","cost":[]},"event":[],"children":[],"photos":[]},{"id":"B0HUBCGJB8","parent":[],"childtype":[],"name":"邻嘉城运邻里中心充电站","tag":[],"type":"汽车服务;充电站;充电站","typecode":"011100","biz_type":[],"address":"翠湖二路与木鱼山大道交叉口东北180米","location":"117.868641,30.954133","tel":[],"postcode":[],"website":[],"email":[],"pcode":"340000","pname":"安徽省","citycode":"0562","cityname":"铜陵市","adcode":"340705","adname":"铜官区","importance":[],"shopid":[],"shopinfo":"0","poiweight":[],"gridcode":"4617364911","distance":[],"navi_poiid":[],"entr_location":"117.868641,30.954249","business_area":[],"exit_location":[],"match":"0","recommend":"0","timestamp":"2022-06-29 20:44:11","alias":[],"indoor_map":"0","indoor_data":{"cpid":[],"floor":[],"truefloor":[],"cmsid":[]},"groupbuy_num":"0","discount_num":"0","biz_ext":{"rating":[],"cost":[]},"event":[],"children":[],"photos":[]},{"id":"B0FFIN33H2","parent":[],"childtype":[],"name":"特斯拉目的地充电站(铜陵柏庄香域站)","tag":[],"type":"汽车服务;充电站;充电站","typecode":"011100","biz_type":[],"address":"铜井西路2701号铜陵柏庄香域门口停车场","location":"117.857461,30.934648","tel":[],"postcode":[],"website":[],"email":[],"pcode":"340000","pname":"安徽省","citycode":"0562","cityname":"铜陵市","adcode":"340705","adname":"铜官区","importance":[],"shopid":[],"shopinfo":"0","poiweight":[],"gridcode":"4617362801","distance":[],"navi_poiid":[],"entr_location":"117.857474,30.93467","business_area":[],"exit_location":[],"match":"0","recommend":"0","timestamp":"2023-04-16 15:34:12","alias":[],"indoor_map":"0","indoor_data":{"cpid":[],"floor":[],"truefloor":[],"cmsid":[]},"groupbuy_num":"0","discount_num":"0","biz_ext":{"rating":"0.8","cost":[]},"event":[],"children":[],"photos":[]},{"id":"B0IAFZ7NR8","parent":"B0GK2HHRFC","childtype":"313","name":"汽车充电站(铜陵万达广场小鹏超充站)","tag":[],"type":"汽车服务;充电站;充电站","typecode":"011100","biz_type":[],"address":"万达广场地下B1层G区(入口庙冲路)052车位,安徽省铜陵市铜官区石城大道中段599号","location":"117.829579,30.943913","tel":"4008193388","postcode":[],"website":[],"email":[],"pcode":"340000","pname":"安徽省","citycode":"0562","cityname":"铜陵市","adcode":"340705","adname":"铜官区","importance":[],"shopid":[],"shopinfo":"0","poiweight":[],"gridcode":"4617363601","distance":[],"navi_poiid":[],"entr_location":"117.829479,30.943754","business_area":"石城大道中段","exit_location":[],"match":"0","recommend":"0","timestamp":"2023-04-20 07:51:24","alias":[],"indoor_map":"0","indoor_data":{"cpid":[],"floor":[],"truefloor":[],"cmsid":[]},"groupbuy_num":"0","discount_num":"0","biz_ext":{"rating":"4.4","cost":[]},"event":[],"children":[],"photos":[{"title":"1","url":"http://store.is.autonavi.com/showpic/a3bd100f2f8e6e8c042acd36efede690"},{"title":"1","url":"http://store.is.autonavi.com/showpic/1d9c71d6e6ba32b0878a25b07d9a1703"},{"title":"1","url":"http://store.is.autonavi.com/showpic/01748d9c9a2312782c96552f5ddcd7f6"}]},{"id":"B0IGB5LDT0","parent":[],"childtype":[],"name":"国家电网汽车充电站(安徽省铜陵市铜官区铜都大道中石化加油站充电站)","tag":[],"type":"汽车服务;充电站;充电站","typecode":"011100","biz_type":[],"address":"桥南街道中国石化铜陵顺达加油站","location":"117.812075,30.913743","tel":[],"postcode":[],"website":[],"email":[],"pcode":"340000","pname":"安徽省","citycode":"0562","cityname":"铜陵市","adcode":"340711","adname":"郊区","importance":[],"shopid":[],"shopinfo":"0","poiweight":[],"gridcode":"4617269412","distance":[],"navi_poiid":[],"entr_location":"117.811868,30.913938","business_area":[],"exit_location":[],"match":"0","recommend":"0","timestamp":"2023-04-20 08:19:54","alias":[],"indoor_map":"0","indoor_data":{"cpid":[],"floor":[],"truefloor":[],"cmsid":[]},"groupbuy_num":"0","discount_num":"0","biz_ext":{"rating":"1.9","cost":[]},"event":[],"children":[],"photos":[]},{"id":"B0IBH5DPQB","parent":"B023201AXM","childtype":"313","name":"国家电网汽车充电站(安徽省铜陵市高铁站停车场充电站)","tag":[],"type":"汽车服务;充电站;充电站","typecode":"011100","biz_type":[],"address":"西湖镇广场南路铜陵站停车场","location":"117.860000,30.917807","tel":[],"postcode":[],"website":[],"email":[],"pcode":"340000","pname":"安徽省","citycode":"0562","cityname":"铜陵市","adcode":"340705","adname":"铜官区","importance":[],"shopid":[],"shopinfo":"0","poiweight":[],"gridcode":"4617360802","distance":[],"navi_poiid":[],"entr_location":"117.8599,30.91783","business_area":[],"exit_location":[],"match":"0","recommend":"0","timestamp":"2023-04-20 08:19:54","alias":[],"indoor_map":"0","indoor_data":{"cpid":[],"floor":[],"truefloor":[],"cmsid":[]},"groupbuy_num":"0","discount_num":"0","biz_ext":{"rating":"4.4","cost":[]},"event":[],"children":[],"photos":[]},{"id":"B0FFKZH9DE","parent":[],"childtype":[],"name":"星星充电汽车充电站(铜陵百世物流有限公司)","tag":[],"type":"汽车服务;充电站;充电站","typecode":"011100","biz_type":[],"address":"交警二大队隔壁院内","location":"117.852552,30.947674","tel":"4008280768","postcode":[],"website":[],"email":[],"pcode":"340000","pname":"安徽省","citycode":"0562","cityname":"铜陵市","adcode":"340705","adname":"铜官区","importance":[],"shopid":[],"shopinfo":"0","poiweight":[],"gridcode":"4617363820","distance":[],"navi_poiid":[],"entr_location":"117.852587,30.947717","business_area":[],"exit_location":[],"match":"0","recommend":"0","timestamp":"2023-04-20 07:01:33","alias":[],"indoor_map":"0","indoor_data":{"cpid":[],"floor":[],"truefloor":[],"cmsid":[]},"groupbuy_num":"0","discount_num":"0","biz_ext":{"rating":"1.5","cost":[]},"event":[],"children":[],"photos":[{"title":[],"url":"http://store.is.autonavi.com/showpic/6752bf5fdc7a6dc290ed0a151ff1c656"}]},{"id":"B0J6CRMF05","parent":[],"childtype":[],"name":"特来电充电站(铜陵吾悦广场)","tag":[],"type":"汽车服务;充电站;充电站","typecode":"011100","biz_type":[],"address":"西湖镇铜陵吾悦广场地下一层B5区121-127车位","location":"117.868454,30.951553","tel":"4001300001","postcode":[],"website":[],"email":[],"pcode":"340000","pname":"安徽省","citycode":"0562","cityname":"铜陵市","adcode":"340705","adname":"铜官区","importance":[],"shopid":[],"shopinfo":"0","poiweight":[],"gridcode":"4617364901","distance":[],"navi_poiid":[],"entr_location":[],"business_area":[],"exit_location":[],"match":"0","recommend":"0","timestamp":"2023-04-18 16:08:08","alias":[],"indoor_map":"0","indoor_data":{"cpid":[],"floor":[],"truefloor":[],"cmsid":[]},"groupbuy_num":"0","discount_num":"0","biz_ext":{"rating":"4.5","cost":[]},"event":[],"children":[],"photos":[{"title":[],"url":"http://store.is.autonavi.com/showpic/ddb575dca4793bd779356881cce09957"},{"title":[],"url":"http://store.is.autonavi.com/showpic/f5b4ffa576a290f134fbc256a2e6ac65"},{"title":[],"url":"http://store.is.autonavi.com/showpic/a686be757939e5353938b94ae2e3648a"}]},{"id":"B0FFLKW8JV","parent":[],"childtype":[],"name":"怪兽充电(老站农家院)","tag":[],"type":"生活服务;共享设备;充电宝","typecode":"072101","biz_type":[],"address":"铜官大道北段与北京西路辅路交叉口西120米","location":"117.816373,30.941719","tel":[],"postcode":[],"website":[],"email":[],"pcode":"340000","pname":"安徽省","citycode":"0562","cityname":"铜陵市","adcode":"340705","adname":"铜官区","importance":[],"shopid":[],"shopinfo":"0","poiweight":[],"gridcode":"4617363500","distance":[],"navi_poiid":[],"entr_location":"117.816185,30.941832","business_area":[],"exit_location":[],"match":"0","recommend":"0","timestamp":"2022-07-27 03:03:23","alias":[],"indoor_map":"0","indoor_data":{"cpid":[],"floor":[],"truefloor":[],"cmsid":[]},"groupbuy_num":"0","discount_num":"0","biz_ext":{"rating":"3.3","cost":[]},"event":[],"children":[],"photos":[]},{"id":"B0I2K6I37Q","parent":[],"childtype":[],"name":"特来电充电站(邻嘉城运长江路停车场)","tag":[],"type":"汽车服务;充电站;充电站","typecode":"011100","biz_type":[],"address":"铜官山区虚镇长江东路56号","location":"117.820112,30.923465","tel":"4001300001","postcode":[],"website":[],"email":[],"pcode":"340000","pname":"安徽省","citycode":"0562","cityname":"铜陵市","adcode":"340705","adname":"铜官区","importance":[],"shopid":[],"shopinfo":"0","poiweight":[],"gridcode":"4617360521","distance":[],"navi_poiid":[],"entr_location":"117.819982,30.923333","business_area":"铜都大道","exit_location":[],"match":"0","recommend":"0","timestamp":"2023-04-18 16:05:16","alias":[],"indoor_map":"0","indoor_data":{"cpid":[],"floor":[],"truefloor":[],"cmsid":[]},"groupbuy_num":"0","discount_num":"0","biz_ext":{"rating":"4.1","cost":[]},"event":[],"children":[],"photos":[{"title":[],"url":"http://store.is.autonavi.com/showpic/c94aa35aae769eea9e068249dcc0d550"},{"title":[],"url":"http://store.is.autonavi.com/showpic/32114324ab497bdfa4c9ac31304423e7"},{"title":[],"url":"http://store.is.autonavi.com/showpic/378193050b133b116878e1441301f586"}]},{"id":"B0G066JHNN","parent":[],"childtype":[],"name":"特来电充电站(邻嘉城运锦湖园)","tag":[],"type":"汽车服务;充电站;充电站","typecode":"011100","biz_type":[],"address":"铜官山区虚镇园林路锦湖园(铜官大道中段)","location":"117.797240,30.931710","tel":"4001300001","postcode":[],"website":[],"email":[],"pcode":"340000","pname":"安徽省","citycode":"0562","cityname":"铜陵市","adcode":"340705","adname":"铜官区","importance":[],"shopid":[],"shopinfo":"0","poiweight":[],"gridcode":"4617361322","distance":[],"navi_poiid":[],"entr_location":"117.797144,30.93165","business_area":[],"exit_location":[],"match":"0","recommend":"0","timestamp":"2023-04-18 16:03:06","alias":[],"indoor_map":"0","indoor_data":{"cpid":[],"floor":[],"truefloor":[],"cmsid":[]},"groupbuy_num":"0","discount_num":"0","biz_ext":{"rating":"4.1","cost":[]},"event":[],"children":[],"photos":[{"title":[],"url":"http://store.is.autonavi.com/showpic/a12cc5cdb78f423f0a28dc4befe5c3a4"},{"title":[],"url":"http://store.is.autonavi.com/showpic/cc086f7506870364eee87e73e878a6fe"}]},{"id":"B0IKHDBIUL","parent":[],"childtype":[],"name":"星星充电汽车充电站(易充科技铜陵国际汽车城站)","tag":[],"type":"汽车服务;充电站;充电站","typecode":"011100","biz_type":[],"address":"西湖镇创客公寓铜陵国际汽车城","location":"117.900450,30.938130","tel":"4008280768","postcode":[],"website":[],"email":[],"pcode":"340000","pname":"安徽省","citycode":"0562","cityname":"铜陵市","adcode":"340705","adname":"铜官区","importance":[],"shopid":[],"shopinfo":"0","poiweight":[],"gridcode":"4617372210","distance":[],"navi_poiid":[],"entr_location":[],"business_area":[],"exit_location":[],"match":"0","recommend":"0","timestamp":"2023-04-20 08:19:54","alias":[],"indoor_map":"0","indoor_data":{"cpid":[],"floor":[],"truefloor":[],"cmsid":[]},"groupbuy_num":"0","discount_num":"0","biz_ext":{"rating":"1.8","cost":[]},"event":[],"children":[],"photos":[{"title":"1","url":"http://store.is.autonavi.com/showpic/f38197c7b966ee0bcc40d3797ae9987d"},{"title":"1","url":"http://store.is.autonavi.com/showpic/797af4ea3df581315529a893ad09bca3"},{"title":"1","url":"http://store.is.autonavi.com/showpic/49528e9d66b88246a60c1e7c1cd957f6"}]},{"id":"B0FFLLLE1U","parent":[],"childtype":[],"name":"怪兽充电(金灿灿茶艺会所)","tag":[],"type":"生活服务;共享设备;充电宝","typecode":"072101","biz_type":[],"address":"铜官大道北段53号(老火车站旁50米)","location":"117.816236,30.940897","tel":[],"postcode":[],"website":[],"email":[],"pcode":"340000","pname":"安徽省","citycode":"0562","cityname":"铜陵市","adcode":"340705","adname":"铜官区","importance":[],"shopid":[],"shopinfo":"0","poiweight":[],"gridcode":"4617362520","distance":[],"navi_poiid":[],"entr_location":[],"business_area":[],"exit_location":[],"match":"0","recommend":"0","timestamp":"2022-07-14 04:54:52","alias":[],"indoor_map":"0","indoor_data":{"cpid":[],"floor":[],"truefloor":[],"cmsid":[]},"groupbuy_num":"0","discount_num":"0","biz_ext":{"rating":"3.3","cost":[]},"event":[],"children":[],"photos":[]},{"id":"B0HKV47ZRM","parent":[],"childtype":[],"name":"特来电充电站(邻嘉城运翠湖公园)","tag":[],"type":"汽车服务;充电站;充电站","typecode":"011100","biz_type":[],"address":"翠湖二路翠湖公园停车场内","location":"117.833749,30.955937","tel":"4001300001","postcode":[],"website":[],"email":[],"pcode":"340000","pname":"安徽省","citycode":"0562","cityname":"铜陵市","adcode":"340705","adname":"铜官区","importance":[],"shopid":[],"shopinfo":"0","poiweight":[],"gridcode":"4617364622","distance":[],"navi_poiid":[],"entr_location":"117.833575,30.95602","business_area":[],"exit_location":[],"match":"0","recommend":"0","timestamp":"2023-04-18 16:03:35","alias":[],"indoor_map":"0","indoor_data":{"cpid":[],"floor":[],"truefloor":[],"cmsid":[]},"groupbuy_num":"0","discount_num":"0","biz_ext":{"rating":"5.0","cost":[]},"event":[],"children":[],"photos":[{"title":[],"url":"http://store.is.autonavi.com/showpic/1b7c183dd1f1cb247a1ca4f57d8b4aa4"},{"title":[],"url":"http://store.is.autonavi.com/showpic/7e91db9cbd175568540f7c470e149025"},{"title":[],"url":"http://store.is.autonavi.com/showpic/2b392f85a0304cffacfe245ef392fe4a"}]},{"id":"B0JA7DUYW2","parent":[],"childtype":[],"name":"特来电充电站(邻嘉铜陵市公安局)","tag":[],"type":"汽车服务;充电站;充电站","typecode":"011100","biz_type":[],"address":"华山大道","location":"117.824407,30.955534","tel":"4001300001","postcode":[],"website":[],"email":[],"pcode":"340000","pname":"安徽省","citycode":"0562","cityname":"铜陵市","adcode":"340705","adname":"铜官区","importance":[],"shopid":[],"shopinfo":"0","poiweight":[],"gridcode":"4617364512","distance":[],"navi_poiid":[],"entr_location":[],"business_area":[],"exit_location":[],"match":"0","recommend":"0","timestamp":"2023-04-20 03:35:12","alias":[],"indoor_map":"0","indoor_data":{"cpid":[],"floor":[],"truefloor":[],"cmsid":[]},"groupbuy_num":"0","discount_num":"0","biz_ext":{"rating":[],"cost":[]},"event":[],"children":[],"photos":[{"title":[],"url":"http://store.is.autonavi.com/showpic/892323b0f7b153af2ce89d7d92e08633"},{"title":[],"url":"http://store.is.autonavi.com/showpic/93c840cebd168a7182d849103e145e0d"},{"title":[],"url":"http://store.is.autonavi.com/showpic/5cf5f6d16c7f7cc82e63aad5653c1c52"}]},{"id":"B0HUFUVGYP","parent":"B0HKKULV3B","childtype":"313","name":"特来电充电站(邻嘉城运体育中心)","tag":[],"type":"汽车服务;充电站;充电站","typecode":"011100","biz_type":[],"address":"体育中心","location":"117.862880,30.965619","tel":"17398319220;4001300001","postcode":[],"website":[],"email":[],"pcode":"340000","pname":"安徽省","citycode":"0562","cityname":"铜陵市","adcode":"340705","adname":"铜官区","importance":[],"shopid":[],"shopinfo":"0","poiweight":[],"gridcode":"4617365920","distance":[],"navi_poiid":[],"entr_location":"117.862778,30.965629","business_area":[],"exit_location":[],"match":"0","recommend":"0","timestamp":"2023-04-18 16:07:37","alias":[],"indoor_map":"0","indoor_data":{"cpid":[],"floor":[],"truefloor":[],"cmsid":[]},"groupbuy_num":"0","discount_num":"0","biz_ext":{"rating":"4.5","cost":[]},"event":[],"children":[],"photos":[{"title":[],"url":"http://store.is.autonavi.com/showpic/dbd7914ffc0ec7ee8bca855ca0b5af2f"},{"title":[],"url":"http://store.is.autonavi.com/showpic/17fddacfe5fbc987a24e1311330ddc1b"},{"title":[],"url":"http://store.is.autonavi.com/showpic/aa02929f3a7021da8038e705f97649fa"}]},{"id":"B0HRG49ID1","parent":[],"childtype":[],"name":"特来电充电站(文景大厦)","tag":[],"type":"汽车服务;充电站;充电站","typecode":"011100","biz_type":[],"address":"东郊街道铜都大道北段5268号联盟新苑","location":"117.835248,30.929802","tel":"15756017779","postcode":[],"website":[],"email":[],"pcode":"340000","pname":"安徽省","citycode":"0562","cityname":"铜陵市","adcode":"340705","adname":"铜官区","importance":[],"shopid":[],"shopinfo":"0","poiweight":[],"gridcode":"4617361612","distance":[],"navi_poiid":[],"entr_location":[],"business_area":"铜都大道","exit_location":[],"match":"0","recommend":"0","timestamp":"2023-04-18 16:10:12","alias":[],"indoor_map":"0","indoor_data":{"cpid":[],"floor":[],"truefloor":[],"cmsid":[]},"groupbuy_num":"0","discount_num":"0","biz_ext":{"rating":"2.3","cost":[]},"event":[],"children":[],"photos":[{"title":[],"url":"http://store.is.autonavi.com/showpic/cd734586f5472efb8329262beeffa0d9"},{"title":[],"url":"http://store.is.autonavi.com/showpic/f1f376962f927b9351e8a36c2b67fe16"},{"title":[],"url":"http://store.is.autonavi.com/showpic/f9dea39240e38930511071647cc8c8a7"}]},{"id":"B0H1A41PD1","parent":[],"childtype":[],"name":"特来电充电站(邻嘉城运万锦)","tag":[],"type":"汽车服务;充电站;充电站","typecode":"011100","biz_type":[],"address":"铜井西路万锦新城B区","location":"117.831453,30.941918","tel":"4001300001","postcode":[],"website":[],"email":[],"pcode":"340000","pname":"安徽省","citycode":"0562","cityname":"铜陵市","adcode":"340705","adname":"铜官区","importance":[],"shopid":[],"shopinfo":"0","poiweight":[],"gridcode":"4617363601","distance":[],"navi_poiid":[],"entr_location":"117.831697,30.941866","business_area":"石城大道中段","exit_location":[],"match":"0","recommend":"0","timestamp":"2023-04-18 16:07:18","alias":[],"indoor_map":"0","indoor_data":{"cpid":[],"floor":[],"truefloor":[],"cmsid":[]},"groupbuy_num":"0","discount_num":"0","biz_ext":{"rating":"4.1","cost":[]},"event":[],"children":[],"photos":[{"title":[],"url":"http://store.is.autonavi.com/showpic/35156f8f77b4c795224b47a434421818"},{"title":[],"url":"http://store.is.autonavi.com/showpic/39925f562f2e7bb118ad7ff44728607d"},{"title":[],"url":"http://store.is.autonavi.com/showpic/7115fc66714bc2c1dc341a4b23f4c6fc"}]},{"id":"B0GUL5RDOV","parent":[],"childtype":[],"name":"特来电充电站(邻嘉城运北斗西路)","tag":[],"type":"汽车服务;充电站;充电站","typecode":"011100","biz_type":[],"address":"湖东路辅路","location":"117.813525,30.945274","tel":"17398319220","postcode":[],"website":[],"email":[],"pcode":"340000","pname":"安徽省","citycode":"0562","cityname":"铜陵市","adcode":"340705","adname":"铜官区","importance":[],"shopid":[],"shopinfo":"0","poiweight":[],"gridcode":"4617363510","distance":[],"navi_poiid":[],"entr_location":"117.813871,30.944633","business_area":[],"exit_location":[],"match":"0","recommend":"0","timestamp":"2023-04-18 16:05:38","alias":[],"indoor_map":"0","indoor_data":{"cpid":[],"floor":[],"truefloor":[],"cmsid":[]},"groupbuy_num":"0","discount_num":"0","biz_ext":{"rating":"5.0","cost":[]},"event":[],"children":[],"photos":[{"title":[],"url":"http://store.is.autonavi.com/showpic/dde87d4f154b272cb4fa087dc0b0d1a8"},{"title":[],"url":"http://store.is.autonavi.com/showpic/1944069b39010a18247953bb9394b166"},{"title":[],"url":"http://store.is.autonavi.com/showpic/963d6db40e5103ab1a53814cf45df026"}]},{"id":"B0GUK5FG36","parent":[],"childtype":[],"name":"特来电充电站(邻嘉城运淮河路)","tag":[],"type":"汽车服务;充电站;充电站","typecode":"011100","biz_type":[],"address":"淮河大道北段-436号","location":"117.813255,30.932402","tel":"17398319220","postcode":[],"website":[],"email":[],"pcode":"340000","pname":"安徽省","citycode":"0562","cityname":"铜陵市","adcode":"340705","adname":"铜官区","importance":[],"shopid":[],"shopinfo":"0","poiweight":[],"gridcode":"4617361520","distance":[],"navi_poiid":[],"entr_location":"117.813307,30.932287","business_area":"淮河路","exit_location":[],"match":"0","recommend":"0","timestamp":"2023-04-18 16:07:50","alias":[],"indoor_map":"0","indoor_data":{"cpid":[],"floor":[],"truefloor":[],"cmsid":[]},"groupbuy_num":"0","discount_num":"0","biz_ext":{"rating":"4.5","cost":[]},"event":[],"children":[],"photos":[{"title":[],"url":"http://store.is.autonavi.com/showpic/a8101ea5270750ad7efd99b249bc71d0"},{"title":[],"url":"http://store.is.autonavi.com/showpic/b09925662ceca14ba9b9d693e3e2fe6f"},{"title":[],"url":"http://store.is.autonavi.com/showpic/f96a29a8cf465fa1685e7689c41a7071"}]},{"id":"B0GKM5SZEW","parent":"B0HR4UXSYV","childtype":"313","name":"特来电充电站(邻嘉城运投资大厦)","tag":[],"type":"汽车服务;充电站;充电站","typecode":"011100","biz_type":[],"address":"投资大厦停车场","location":"117.845794,30.940354","tel":"4001300001","postcode":[],"website":[],"email":[],"pcode":"340000","pname":"安徽省","citycode":"0562","cityname":"铜陵市","adcode":"340705","adname":"铜官区","importance":[],"shopid":[],"shopinfo":"0","poiweight":[],"gridcode":"4617362721","distance":[],"navi_poiid":[],"entr_location":"117.845933,30.940299","business_area":[],"exit_location":[],"match":"0","recommend":"0","timestamp":"2023-04-18 16:06:51","alias":[],"indoor_map":"0","indoor_data":{"cpid":[],"floor":[],"truefloor":[],"cmsid":[]},"groupbuy_num":"0","discount_num":"0","biz_ext":{"rating":"4.5","cost":[]},"event":[],"children":[],"photos":[{"title":[],"url":"http://store.is.autonavi.com/showpic/4552f63301d4fd0cc6fac577133cc8b0"},{"title":[],"url":"http://store.is.autonavi.com/showpic/1cd3e0c4e27d28865e92f45c7a5f9005"},{"title":[],"url":"http://store.is.autonavi.com/showpic/db14044d25590a6c53fd0133892fec11"}]},{"id":"B0G365NLBI","parent":[],"childtype":[],"name":"特来电充电站(邻嘉城运和平停车场)","tag":[],"type":"汽车服务;充电站;充电站","typecode":"011100","biz_type":[],"address":"笔架山路","location":"117.824474,30.918132","tel":[],"postcode":[],"website":[],"email":[],"pcode":"340000","pname":"安徽省","citycode":"0562","cityname":"铜陵市","adcode":"340705","adname":"铜官区","importance":[],"shopid":[],"shopinfo":"0","poiweight":[],"gridcode":"4617360502","distance":[],"navi_poiid":[],"entr_location":"117.824606,30.918142","business_area":[],"exit_location":[],"match":"0","recommend":"0","timestamp":"2023-04-18 16:09:15","alias":[],"indoor_map":"0","indoor_data":{"cpid":[],"floor":[],"truefloor":[],"cmsid":[]},"groupbuy_num":"0","discount_num":"0","biz_ext":{"rating":"4.5","cost":[]},"event":[],"children":[],"photos":[{"title":[],"url":"http://store.is.autonavi.com/showpic/a79c228f4fff538ffdbf9367b9822e1b"},{"title":[],"url":"http://store.is.autonavi.com/showpic/fa1a5b0fbac8c832fc8c65e415de4a31"},{"title":[],"url":"http://store.is.autonavi.com/showpic/18de35c79d2b5f28f79a7981637701e0"}]},{"id":"B0FFKJ0MUX","parent":[],"childtype":[],"name":"怪兽充电(满地可茶楼)","tag":[],"type":"生活服务;共享设备;充电宝","typecode":"072101","biz_type":[],"address":"翠湖一路205号铜陵凤凰城四层2号(凤凰城加油站对面)","location":"117.813391,30.953187","tel":[],"postcode":[],"website":[],"email":[],"pcode":"340000","pname":"安徽省","citycode":"0562","cityname":"铜陵市","adcode":"340705","adname":"铜官区","importance":[],"shopid":[],"shopinfo":"0","poiweight":[],"gridcode":"4617364510","distance":[],"navi_poiid":[],"entr_location":[],"business_area":[],"exit_location":[],"match":"0","recommend":"0","timestamp":"2022-07-13 23:36:10","alias":[],"indoor_map":"0","indoor_data":{"cpid":[],"floor":[],"truefloor":[],"cmsid":[]},"groupbuy_num":"0","discount_num":"0","biz_ext":{"rating":"3.3","cost":[]},"event":[],"children":[],"photos":[]},{"id":"B0HDL4X8GZ","parent":[],"childtype":[],"name":"特来电充电站(邻嘉城运邻里中心)","tag":[],"type":"汽车服务;充电站;充电站","typecode":"011100","biz_type":[],"address":"木鱼山大道与凤祥路交叉口","location":"117.868560,30.954197","tel":"17398319220","postcode":[],"website":[],"email":[],"pcode":"340000","pname":"安徽省","citycode":"0562","cityname":"铜陵市","adcode":"340705","adname":"铜官区","importance":[],"shopid":[],"shopinfo":"0","poiweight":[],"gridcode":"4617364911","distance":[],"navi_poiid":[],"entr_location":"117.868559,30.954249","business_area":[],"exit_location":[],"match":"0","recommend":"0","timestamp":"2023-04-18 16:09:33","alias":[],"indoor_map":"0","indoor_data":{"cpid":[],"floor":[],"truefloor":[],"cmsid":[]},"groupbuy_num":"0","discount_num":"0","biz_ext":{"rating":"5.0","cost":[]},"event":[],"children":[],"photos":[{"title":[],"url":"http://store.is.autonavi.com/showpic/c86fc77d774be54956093b13fb00cceb"},{"title":[],"url":"http://store.is.autonavi.com/showpic/79bc323919973c10915a372eb6052b32"},{"title":[],"url":"http://store.is.autonavi.com/showpic/72cbd6e45f92d26dce4426c8d235088a"}]},{"id":"B0IKHDE7WS","parent":[],"childtype":[],"name":"特来电充电站(邻嘉城运公租房运营服务中心)","tag":[],"type":"汽车服务;充电站;充电站","typecode":"011100","biz_type":[],"address":"公租房运营服务中心","location":"117.813680,30.933830","tel":"4001300001","postcode":[],"website":[],"email":[],"pcode":"340000","pname":"安徽省","citycode":"0562","cityname":"铜陵市","adcode":"340705","adname":"铜官区","importance":[],"shopid":[],"shopinfo":"0","poiweight":[],"gridcode":"4617362500","distance":[],"navi_poiid":[],"entr_location":[],"business_area":"义安路","exit_location":[],"match":"0","recommend":"0","timestamp":"2023-04-18 16:03:54","alias":[],"indoor_map":"0","indoor_data":{"cpid":[],"floor":[],"truefloor":[],"cmsid":[]},"groupbuy_num":"0","discount_num":"0","biz_ext":{"rating":"2.3","cost":[]},"event":[],"children":[],"photos":[{"title":[],"url":"http://store.is.autonavi.com/showpic/7ff223708a1f36cb962648ed791e2254"},{"title":[],"url":"http://store.is.autonavi.com/showpic/a1781b799a3d41767adcf297d7e8e9cf"},{"title":[],"url":"http://store.is.autonavi.com/showpic/fbed61983c984cacf7dde1e9a255c677"}]},{"id":"B0I2FRRJRM","parent":"B0FFG9JFWG","childtype":"313","name":"特来电充电站(邻嘉城运义安大道)","tag":[],"type":"汽车服务;充电站;充电站","typecode":"011100","biz_type":[],"address":"义安大道北段835号院内","location":"117.817062,30.931743","tel":"4001300001","postcode":[],"website":[],"email":[],"pcode":"340000","pname":"安徽省","citycode":"0562","cityname":"铜陵市","adcode":"340705","adname":"铜官区","importance":[],"shopid":[],"shopinfo":"0","poiweight":[],"gridcode":"4617361521","distance":[],"navi_poiid":[],"entr_location":"117.817321,30.931648","business_area":"义安路","exit_location":[],"match":"0","recommend":"0","timestamp":"2023-04-18 16:08:13","alias":[],"indoor_map":"0","indoor_data":{"cpid":[],"floor":[],"truefloor":[],"cmsid":[]},"groupbuy_num":"0","discount_num":"0","biz_ext":{"rating":"4.5","cost":[]},"event":[],"children":[],"photos":[{"title":[],"url":"http://store.is.autonavi.com/showpic/883c813a5a8c5600e4476ca97e7ba3ab"},{"title":[],"url":"http://store.is.autonavi.com/showpic/a549110e59e451b1c36ca3ac39c3ca6d"},{"title":[],"url":"http://store.is.autonavi.com/showpic/e131e47c88a0590d0f243a970b56031d"}]},{"id":"B0I2667OOR","parent":"B0I1VSVUXL","childtype":"313","name":"特来电充电站(邻嘉城运学院路)","tag":[],"type":"汽车服务;充电站;充电站","typecode":"011100","biz_type":[],"address":"学院路停车场(学院路正阳四季学校西侧)","location":"117.830427,30.934515","tel":"4001300001","postcode":[],"website":[],"email":[],"pcode":"340000","pname":"安徽省","citycode":"0562","cityname":"铜陵市","adcode":"340705","adname":"铜官区","importance":[],"shopid":[],"shopinfo":"0","poiweight":[],"gridcode":"4617362601","distance":[],"navi_poiid":[],"entr_location":"117.830453,30.934454","business_area":[],"exit_location":[],"match":"0","recommend":"0","timestamp":"2023-04-18 16:06:42","alias":[],"indoor_map":"0","indoor_data":{"cpid":[],"floor":[],"truefloor":[],"cmsid":[]},"groupbuy_num":"0","discount_num":"0","biz_ext":{"rating":"5.0","cost":[]},"event":[],"children":[],"photos":[{"title":[],"url":"http://store.is.autonavi.com/showpic/ee7af1c46c063f5ec117435c9c59e078"},{"title":[],"url":"http://store.is.autonavi.com/showpic/d58b3623f166575f1ce2c03baadc7b92"},{"title":[],"url":"http://store.is.autonavi.com/showpic/9895c48bae315b268744b793b6f223e8"}]},{"id":"B0FFLLCRBH","parent":[],"childtype":[],"name":"怪兽充电(开发区休闲驿站)","tag":[],"type":"生活服务;共享设备;充电宝","typecode":"072101","biz_type":[],"address":"开发区泰山大道1051号","location":"117.830056,30.973230","tel":[],"postcode":[],"website":[],"email":[],"pcode":"340000","pname":"安徽省","citycode":"0562","cityname":"铜陵市","adcode":"340705","adname":"铜官区","importance":[],"shopid":[],"shopinfo":"0","poiweight":[],"gridcode":"4617366621","distance":[],"navi_poiid":[],"entr_location":"117.830243,30.973116","business_area":[],"exit_location":[],"match":"0","recommend":"0","timestamp":"2022-07-14 00:53:32","alias":[],"indoor_map":"0","indoor_data":{"cpid":[],"floor":[],"truefloor":[],"cmsid":[]},"groupbuy_num":"0","discount_num":"0","biz_ext":{"rating":"3.3","cost":[]},"event":[],"children":[],"photos":[]},{"id":"B0JGTUVR7P","parent":[],"childtype":[],"name":"铜陵精达综合智慧能源项目","tag":[],"type":"汽车服务;充电站;充电站","typecode":"011100","biz_type":[],"address":"铜官山区虚镇五松社区五松卫生服务站五松花苑住宅小区","location":"117.800000,30.930000","tel":"13851871633","postcode":[],"website":[],"email":[],"pcode":"340000","pname":"安徽省","citycode":"0562","cityname":"铜陵市","adcode":"340705","adname":"铜官区","importance":[],"shopid":[],"shopinfo":"0","poiweight":[],"gridcode":"4617361410","distance":[],"navi_poiid":[],"entr_location":[],"business_area":[],"exit_location":[],"match":"0","recommend":"0","timestamp":"2023-04-11 21:17:16","alias":[],"indoor_map":"0","indoor_data":{"cpid":[],"floor":[],"truefloor":[],"cmsid":[]},"groupbuy_num":"0","discount_num":"0","biz_ext":{"rating":"2.4","cost":[]},"event":[],"children":[],"photos":[]},{"id":"B0IKJ9CXLJ","parent":[],"childtype":[],"name":"国家电网汽车充电站(中石化汽车充电站安徽省铜陵市石城大道加油站充电站)","tag":[],"type":"汽车服务;充电站;充电站","typecode":"011100","biz_type":[],"address":"新城街道西湖二路中国石化石城大道加油站","location":"117.847001,30.993874","tel":"0562-6812017","postcode":[],"website":[],"email":[],"pcode":"340000","pname":"安徽省","citycode":"0562","cityname":"铜陵市","adcode":"340705","adname":"铜官区","importance":[],"shopid":[],"shopinfo":"0","poiweight":[],"gridcode":"4617369702","distance":[],"navi_poiid":[],"entr_location":[],"business_area":[],"exit_location":[],"match":"0","recommend":"0","timestamp":"2023-04-20 09:01:17","alias":[],"indoor_map":"0","indoor_data":{"cpid":[],"floor":[],"truefloor":[],"cmsid":[]},"groupbuy_num":"0","discount_num":"0","biz_ext":{"rating":"1.0","cost":[]},"event":[],"children":[],"photos":[]},{"id":"B0IAL5X4MF","parent":[],"childtype":[],"name":"星星充电汽车充电站(铜陵市保祥物业服务有限公司)","tag":[],"type":"汽车服务;充电站;充电站","typecode":"011100","biz_type":[],"address":"淮河大道中段906铜陵房地产大厦","location":"117.805936,30.923262","tel":"4008280768","postcode":[],"website":[],"email":[],"pcode":"340000","pname":"安徽省","citycode":"0562","cityname":"铜陵市","adcode":"340705","adname":"铜官区","importance":[],"shopid":[],"shopinfo":"0","poiweight":[],"gridcode":"4617360421","distance":[],"navi_poiid":[],"entr_location":"117.805988,30.923587","business_area":"铜庄","exit_location":[],"match":"0","recommend":"0","timestamp":"2023-04-20 10:12:47","alias":[],"indoor_map":"0","indoor_data":{"cpid":[],"floor":[],"truefloor":[],"cmsid":[]},"groupbuy_num":"0","discount_num":"0","biz_ext":{"rating":"1.4","cost":[]},"event":[],"children":[],"photos":[{"title":[],"url":"http://store.is.autonavi.com/showpic/44b6ab2812e3db6443272572d22ebf75"}]},{"id":"B0JBLHR4SX","parent":[],"childtype":[],"name":"汽车充电站(开迈斯充电站铜陵市吾悦广场直流站)","tag":[],"type":"汽车服务;充电站;充电站","typecode":"011100","biz_type":[],"address":"翠湖二路与木鱼山大道交汇处铜陵吾悦广场地下停车场B1层","location":"117.868454,30.951553","tel":"4006657666","postcode":[],"website":[],"email":[],"pcode":"340000","pname":"安徽省","citycode":"0562","cityname":"铜陵市","adcode":"340705","adname":"铜官区","importance":[],"shopid":[],"shopinfo":"0","poiweight":[],"gridcode":"4617364901","distance":[],"navi_poiid":[],"entr_location":[],"business_area":[],"exit_location":[],"match":"0","recommend":"0","timestamp":"2023-04-20 07:49:19","alias":[],"indoor_map":"0","indoor_data":{"cpid":[],"floor":[],"truefloor":[],"cmsid":[]},"groupbuy_num":"0","discount_num":"0","biz_ext":{"rating":"2.5","cost":[]},"event":[],"children":[],"photos":[{"title":[],"url":"http://store.is.autonavi.com/showpic/89d0b53b6f65e4e017e4b1cb67fe2b20"},{"title":[],"url":"http://store.is.autonavi.com/showpic/628e2ff0cb969ecb5689d0f966896125"},{"title":[],"url":"http://store.is.autonavi.com/showpic/13db912a77936ab9b8be24a282d47856"}]},{"id":"B0JAL67S3V","parent":[],"childtype":[],"name":"蔚景云汽车充电站(铜陵精达综合智慧能源项目)","tag":[],"type":"汽车服务;充电站;充电站","typecode":"011100","biz_type":[],"address":"新城街道安徽微芯长江半导体(东门)安徽微芯长江半导体材料有限公司","location":"117.836447,31.003852","tel":"4000826699","postcode":[],"website":[],"email":[],"pcode":"340000","pname":"安徽省","citycode":"0562","cityname":"铜陵市","adcode":"340705","adname":"铜官区","importance":[],"shopid":[],"shopinfo":"0","poiweight":[],"gridcode":"4617460612","distance":[],"navi_poiid":[],"entr_location":[],"business_area":[],"exit_location":[],"match":"0","recommend":"0","timestamp":"2023-04-20 05:24:59","alias":[],"indoor_map":"0","indoor_data":{"cpid":[],"floor":[],"truefloor":[],"cmsid":[]},"groupbuy_num":"0","discount_num":"0","biz_ext":{"rating":[],"cost":[]},"event":[],"children":[],"photos":[]},{"id":"B0J6UHM50F","parent":[],"childtype":[],"name":"开迈斯充电站铜陵市吾悦广场汽车充电站","tag":[],"type":"汽车服务;充电站;充电站","typecode":"011100","biz_type":[],"address":"翠湖二路与木鱼山大道交汇处铜陵吾悦广场地下停车场B1层(A085-A090)","location":"117.868258,30.952058","tel":"0562-2611114;18329065536;4006657666","postcode":[],"website":[],"email":[],"pcode":"340000","pname":"安徽省","citycode":"0562","cityname":"铜陵市","adcode":"340705","adname":"铜官区","importance":[],"shopid":[],"shopinfo":"0","poiweight":[],"gridcode":"4617364901","distance":[],"navi_poiid":[],"entr_location":[],"business_area":[],"exit_location":[],"match":"0","recommend":"0","timestamp":"2023-04-18 13:00:21","alias":[],"indoor_map":"0","indoor_data":{"cpid":[],"floor":[],"truefloor":[],"cmsid":[]},"groupbuy_num":"0","discount_num":"0","biz_ext":{"rating":"3.2","cost":[]},"event":[],"children":[],"photos":[{"title":[],"url":"http://store.is.autonavi.com/showpic/b43b46694501655f1e40fbb111187b8b"},{"title":[],"url":"http://store.is.autonavi.com/showpic/ae1b1f7606669531b349ac619c5b9372"},{"title":[],"url":"http://store.is.autonavi.com/showpic/06d618693513ac08dd2d77df35393c6f"}]},{"id":"B0IBRNOGPX","parent":[],"childtype":[],"name":"国家电网汽车充电站(铜陵市政务服务中心北停车场充电站)","tag":[],"type":"汽车服务;充电站;充电站","typecode":"011100","biz_type":[],"address":"湖东路666号政务服务中心北停车场","location":"117.810832,30.947814","tel":[],"postcode":[],"website":[],"email":[],"pcode":"340000","pname":"安徽省","citycode":"0562","cityname":"铜陵市","adcode":"340705","adname":"铜官区","importance":[],"shopid":[],"shopinfo":"0","poiweight":[],"gridcode":"4617363422","distance":[],"navi_poiid":[],"entr_location":"117.81005,30.946822","business_area":[],"exit_location":[],"match":"0","recommend":"0","timestamp":"2023-04-20 08:20:12","alias":[],"indoor_map":"0","indoor_data":{"cpid":[],"floor":[],"truefloor":[],"cmsid":[]},"groupbuy_num":"0","discount_num":"0","biz_ext":{"rating":"3.6","cost":[]},"event":[],"children":[],"photos":[]},{"id":"B0IAL5XW9J","parent":[],"childtype":[],"name":"星星充电汽车充电站(铜陵铜官吾悦广场)","tag":[],"type":"汽车服务;充电站;充电站","typecode":"011100","biz_type":[],"address":"木鱼山大道与翠湖二路交口","location":"117.866240,30.952919","tel":"4008280768","postcode":[],"website":[],"email":[],"pcode":"340000","pname":"安徽省","citycode":"0562","cityname":"铜陵市","adcode":"340705","adname":"铜官区","importance":[],"shopid":[],"shopinfo":"0","poiweight":[],"gridcode":"4617364910","distance":[],"navi_poiid":[],"entr_location":[],"business_area":[],"exit_location":[],"match":"0","recommend":"0","timestamp":"2023-04-20 10:06:07","alias":[],"indoor_map":"0","indoor_data":{"cpid":[],"floor":[],"truefloor":[],"cmsid":[]},"groupbuy_num":"0","discount_num":"0","biz_ext":{"rating":"2.5","cost":[]},"event":[],"children":[],"photos":[{"title":[],"url":"http://store.is.autonavi.com/showpic/44b6ab2812e3db6443272572d22ebf75"}]},{"id":"B0IAL5XB9Y","parent":[],"childtype":[],"name":"星星充电汽车充电站(淮矿东方蓝海)","tag":[],"type":"汽车服务;充电站;充电站","typecode":"011100","biz_type":[],"address":"义安区东湖一路和新城大道交叉口","location":"117.846979,30.988163","tel":"4008280768","postcode":[],"website":[],"email":[],"pcode":"340000","pname":"安徽省","citycode":"0562","cityname":"铜陵市","adcode":"340705","adname":"铜官区","importance":[],"shopid":[],"shopinfo":"0","poiweight":[],"gridcode":"4617368712","distance":[],"navi_poiid":[],"entr_location":[],"business_area":[],"exit_location":[],"match":"0","recommend":"0","timestamp":"2023-04-19 16:10:24","alias":[],"indoor_map":"0","indoor_data":{"cpid":[],"floor":[],"truefloor":[],"cmsid":[]},"groupbuy_num":"0","discount_num":"0","biz_ext":{"rating":"2.4","cost":[]},"event":[],"children":[],"photos":[{"title":[],"url":"http://store.is.autonavi.com/showpic/e6244d64ac86294ea2b9f6f676f98ff0"},{"title":[],"url":"http://store.is.autonavi.com/showpic/67656f799105aa5ab948c4649c11a50a"}]},{"id":"B0I0CPF9A3","parent":"B0H307D4JR","childtype":"313","name":"驴充充汽车充电站(绿源大市场3期)","tag":[],"type":"汽车服务;充电站;充电站","typecode":"011100","biz_type":[],"address":"郊区鹊江路806号郊区绿源大市场3期(鹊江路南)","location":"117.853400,30.944225","tel":"4009155388","postcode":[],"website":[],"email":[],"pcode":"340000","pname":"安徽省","citycode":"0562","cityname":"铜陵市","adcode":"340705","adname":"铜官区","importance":[],"shopid":[],"shopinfo":"0","poiweight":[],"gridcode":"4617363800","distance":[],"navi_poiid":[],"entr_location":[],"business_area":[],"exit_location":[],"match":"0","recommend":"0","timestamp":"2023-04-19 05:00:10","alias":[],"indoor_map":"0","indoor_data":{"cpid":[],"floor":[],"truefloor":[],"cmsid":[]},"groupbuy_num":"0","discount_num":"0","biz_ext":{"rating":"1.6","cost":[]},"event":[],"children":[],"photos":[{"title":"1","url":"http://store.is.autonavi.com/showpic/38c54137db753fe15ea38760cbba45f4"}]}]}